ci_matrix_starter/__init__.py
ci_matrix_starter-0.1.10.dist-info/METADATA
ci_matrix_starter-0.1.10.dist-info/WHEEL
ci_matrix_starter-0.1.10.dist-info/licenses/LICENSE
ci_matrix_starter-0.1.10.dist-info/RECORD
