Metadata-Version: 2.4
Name: ci-matrix-starter
Version: 0.1.10
Summary: Starter de CI matrix (Poetry + src layout)
License: MIT
License-File: LICENSE
Author: CoderDeltaLAN
Requires-Python: >=3.11,<4.0
Classifier: License :: OSI Approved :: MIT License
Classifier: Programming Language :: Python :: 3
Classifier: Programming Language :: Python :: 3.11
Classifier: Programming Language :: Python :: 3.12
Classifier: Programming Language :: Python :: 3.13
Classifier: Programming Language :: Python :: 3.14
